RKPairip/Anti_Splits.py
RKPairip/CRC.py
RKPairip/C_M.py
RKPairip/Decompile_Compile.py
RKPairip/Delete_Smali.py
RKPairip/Extract.py
RKPairip/Files_Check.py
RKPairip/Fix_Dex.py
RKPairip/Instruction_Credit.py
RKPairip/Logs_Inject.py
RKPairip/Manifest_Patch.py
RKPairip/Other_Patch.py
RKPairip/RKPairip.py
RKPairip/RK_Pairip.py
RKPairip/Smali_Patch.py
RKPairip/__init__.py
RKPairip/__main__.py
RKPairip/scan.py
rkjp-1.0.dist-info/LICENSE
rkjp-1.0.dist-info/METADATA
rkjp-1.0.dist-info/WHEEL
rkjp-1.0.dist-info/entry_points.txt
rkjp-1.0.dist-info/top_level.txt
rkjp-1.0.dist-info/RECORD
