Metadata-Version: 2.1
Name: rkjp
Version: 1.0
Summary: Recover String & Rebuild Apk
Home-page: https://github.com/Technoindian/RKPairip
Author: RK_TECHNO_INDIA
Author-email: TechnoIndia786@gmail.com
License: MIT
Keywords: RKPairip
Classifier: Programming Language :: Python :: 3
Classifier: License :: OSI Approved :: MIT License
Classifier: Operating System :: OS Independent
Requires-Python: >=3.12
License-File: LICENSE
